{"080001":["SG","080001","Cantonment Road","","","","","","","1.276","103.8414",""],"080003":["SG","080003","Everton Park","","","","","","","1.2772","103.8387",""],"080004":["SG","080004","Everton Park","","","","","","","1.2769","103.8401",""],"080005":["SG","080005","Everton Park","","","","","","","1.2767","103.8395",""],"080006":["SG","080006","Everton Park","","","","","","","1.2767","103.8387",""],"080007":["SG","080007","Everton Park","","","","","","","1.277","103.839",""],"080008":["SG","080008","Tanjong Pagar Plaza","","","","","","","1.2773","103.8429",""],"080009":["SG","080009","Cantonment Close","","","","","","","1.2753","103.8392",""],"080010":["SG","080010","Cantonment Close","","","","","","","1.2746","103.8392",""],"080011":["SG","080011","Cantonment Close","","","","","","","1.2744","103.8397",""],"080012":["SG","080012","Cantonment Close","","","","","","","1.2745","103.8401",""],"080013":["SG","080013","Cantonment Close","","","","","","","1.2747","103.8405",""],"080016":["SG","080016","Cantonment Close","","","","","","","1.2739","103.8403",""],"080017":["SG","080017","Cantonment Close","","","","","","","1.2738","103.8398",""],"080018":["SG","080018","Cantonment Close","","","","","","","1.2739","103.8394",""],"080019":["SG","080019","Cantonment Close","","","","","","","1.2739","103.839",""],"080020":["SG","080020","Cantonment Close","","","","","","","1.2742","103.8396",""],"080101":["SG","080101","Spottiswoode Park Road","","","","","","","1.2752","103.836",""],"080102":["SG","080102","Spottiswoode Park Road","","","","","","","1.2747","103.8362",""],"080103":["SG","080103","Spottiswoode Park Road","","","","","","","1.2747","103.8353",""],"080104":["SG","080104","Spottiswoode Park Road","","","","","","","1.2744","103.8349",""],"080105":["SG","080105","Spottiswoode Park Road","","","","","","","1.2738","103.8345",""],"080106":["SG","080106","Spottiswoode Park Road","","","","","","","1.2736","103.8341",""],"080107":["SG","080107","Spottiswoode Park Road","","","","","","","1.2736","103.8349",""],"080108":["SG","080108","Spottiswoode Park Road","","","","","","","1.2739","103.8357",""],"080109":["SG","080109","Spottiswoode Park Road","","","","","","","1.274","103.8367",""],"080333":["SG","080333","Kreta Ayer Road","","","","","","","1.2807","103.8425",""],"080334":["SG","080334","Kreta Ayer Road","","","","","","","1.2816","103.8423",""]}