{"535001":["SG","535001","Upper Paya Lebar Road","","","","","","","1.3433","103.882",""],"535002":["SG","535002","Upper Paya Lebar Road","","","","","","","1.3434","103.882",""],"535009":["SG","535009","Thrift Drive","","","","","","","1.3425","103.8844",""],"535010":["SG","535010","Thrift Drive","","","","","","","1.3429","103.8845",""],"535011":["SG","535011","Thrift Drive","","","","","","","1.3426","103.8843",""],"535012":["SG","535012","Thrift Drive","","","","","","","1.343","103.8844",""],"535013":["SG","535013","Thrift Drive","","","","","","","1.3426","103.8843",""],"535014":["SG","535014","Thrift Drive","","","","","","","1.3432","103.8843",""],"535015":["SG","535015","Thrift Drive","","","","","","","1.3427","103.8842",""],"535016":["SG","535016","Thrift Drive","","","","","","","1.3433","103.8842",""],"535017":["SG","535017","Thrift Drive","","","","","","","1.3433","103.884",""],"535018":["SG","535018","Thrift Drive","","","","","","","1.3427","103.8842",""],"535019":["SG","535019","Thrift Drive","","","","","","","1.3434","103.884",""],"535020":["SG","535020","Thrift Drive","","","","","","","1.3427","103.8842",""],"535022":["SG","535022","Thrift Drive","","","","","","","1.3428","103.8841",""],"535023":["SG","535023","Thrift Drive","","","","","","","1.3442","103.8836",""],"535024":["SG","535024","Thrift Drive","","","","","","","1.3428","103.8841",""],"535025":["SG","535025","Thrift Drive","","","","","","","1.3443","103.8836",""],"535026":["SG","535026","Thrift Drive","","","","","","","1.3428","103.884",""],"535027":["SG","535027","Thrift Drive","","","","","","","1.3443","103.8835",""],"535028":["SG","535028","Thrift Drive","","","","","","","1.3429","103.884",""],"535029":["SG","535029","Thrift Drive","","","","","","","1.3443","103.8835",""],"535030":["SG","535030","Thrift Drive","","","","","","","1.3429","103.884",""],"535031":["SG","535031","Thrift Drive","","","","","","","1.3444","103.8834",""],"535032":["SG","535032","Thrift Drive","","","","","","","1.343","103.8839",""],"535033":["SG","535033","Thrift Drive","","","","","","","1.3445","103.8834",""],"535034":["SG","535034","Thrift Drive","","","","","","","1.343","103.8839",""],"535035":["SG","535035","Thrift Drive","","","","","","","1.3445","103.8833",""],"535036":["SG","535036","Thrift Drive","","","","","","","1.343","103.8838",""],"535037":["SG","535037","Thrift Drive","","","","","","","1.3446","103.8833",""],"535038":["SG","535038","Thrift Drive","","","","","","","1.3442","103.8832",""],"535039":["SG","535039","Thrift Drive","","","","","","","1.3447","103.8833",""],"535040":["SG","535040","Thrift Drive","","","","","","","1.3442","103.8832",""],"535041":["SG","535041","Thrift Drive","","","","","","","1.3447","103.8832",""],"535042":["SG","535042","Thrift Drive","","","","","","","1.3443","103.8831",""],"535043":["SG","535043","Thrift Drive","","","","","","","1.3443","103.8831",""],"535044":["SG","535044","Thrift Drive","","","","","","","1.3444","103.8831",""],"535045":["SG","535045","Thrift Drive","","","","","","","1.3444","103.883",""],"535046":["SG","535046","Thrift Drive","","","","","","","1.3445","103.883",""],"535047":["SG","535047","Thrift Drive","","","","","","","1.3445","103.883",""],"535048":["SG","535048","Thrift Drive","","","","","","","1.3446","103.883",""],"535049":["SG","535049","Thrift Drive","","","","","","","1.3446","103.8829",""],"535050":["SG","535050","Thrift Drive","","","","","","","1.3447","103.8829",""],"535051":["SG","535051","Thrift Drive","","","","","","","1.3447","103.8829",""],"535052":["SG","535052","Thrift Drive","","","","","","","1.3431","103.8844",""],"535053":["SG","535053","Thrift Drive","","","","","","","1.3432","103.8842",""],"535054":["SG","535054","Thrift Drive","","","","","","","1.3429","103.8845",""],"535066":["SG","535066","Tampines Road","","","","","","","1.3604","103.8865",""],"535067":["SG","535067","Tampines Road","","","","","","","1.3604","103.8867",""],"535068":["SG","535068","Tampines Road","","","","","","","1.3601","103.8868",""],"535069":["SG","535069","Tampines Road","","","","","","","1.3601","103.887",""],"535070":["SG","535070","Tampines Road","","","","","","","1.3603","103.8871",""],"535071":["SG","535071","Tampines Road","","","","","","","1.3602","103.8873",""],"535088":["SG","535088","Tampines Road","","","","","","","1.3607","103.8886",""],"535089":["SG","535089","Tampines Road","","","","","","","1.3607","103.8887",""],"535091":["SG","535091","Tampines Road","","","","","","","1.3607","103.8889",""],"535093":["SG","535093","Tampines Road","","","","","","","1.3607","103.889",""],"535095":["SG","535095","Tampines Road","","","","","","","1.3607","103.8892",""],"535097":["SG","535097","Tampines Road","","","","","","","1.3607","103.8894",""],"535099":["SG","535099","Tampines Road","","","","","","","1.3607","103.8896",""],"535101":["SG","535101","Tampines Road","","","","","","","1.3608","103.8897",""],"535103":["SG","535103","Tampines Road","","","","","","","1.3608","103.8899",""],"535105":["SG","535105","Tampines Road","","","","","","","1.3608","103.8901",""],"535107":["SG","535107","Tampines Road","","","","","","","1.3608","103.8902",""],"535109":["SG","535109","Tampines Road","","","","","","","1.3609","103.8904",""],"535111":["SG","535111","Tampines Road","","","","","","","1.3609","103.8906",""],"535113":["SG","535113","Tampines Road","","","","","","","1.3609","103.8907",""],"535114":["SG","535114","Tampines Road","","","","","","","1.3609","103.8908",""],"535115":["SG","535115","Tampines Road","","","","","","","1.3609","103.8909",""],"535116":["SG","535116","Tampines Road","","","","","","","1.3609","103.8909",""],"535117":["SG","535117","Tampines Road","","","","","","","1.3609","103.8912",""],"535118":["SG","535118","Tampines Road","","","","","","","1.3609","103.8913",""],"535119":["SG","535119","Tampines Road","","","","","","","1.3613","103.8885",""],"535120":["SG","535120","Tampines Road","","","","","","","1.3609","103.8913",""],"535121":["SG","535121","Tampines Road","","","","","","","1.3613","103.889",""],"535122":["SG","535122","Tampines Road","","","","","","","1.3609","103.8914",""],"535123":["SG","535123","Tampines Road","","","","","","","1.3613","103.8891",""],"535124":["SG","535124","Tampines Road","","","","","","","1.3609","103.8914",""],"535125":["SG","535125","Tampines Road","","","","","","","1.3609","103.8915",""],"535126":["SG","535126","Tampines Road","","","","","","","1.361","103.8915",""],"535128":["SG","535128","Tampines Road","","","","","","","1.361","103.8916",""],"535129":["SG","535129","Tampines Road","","","","","","","1.3615","103.8894",""],"535130":["SG","535130","Tampines Road","","","","","","","1.361","103.8916",""],"535131":["SG","535131","Tampines Road","","","","","","","1.3617","103.8908",""],"535132":["SG","535132","Tampines Road","","","","","","","1.361","103.8917",""],"535133":["SG","535133","Tampines Road","","","","","","","1.3618","103.8917",""],"535134":["SG","535134","Tampines Road","","","","","","","1.361","103.8917",""],"535135":["SG","535135","Tampines Road","","","","","","","1.361","103.8918",""],"535136":["SG","535136","Tampines Road","","","","","","","1.3609","103.8926",""],"535137":["SG","535137","Tampines Road","","","","","","","1.3617","103.8921",""],"535138":["SG","535138","Tampines Road","","","","","","","1.3617","103.8921",""],"535139":["SG","535139","Tampines Road","","","","","","","1.3618","103.8921",""],"535140":["SG","535140","Tampines Road","","","","","","","1.3619","103.892",""],"535141":["SG","535141","Tampines Road","","","","","","","1.3619","103.8921",""],"535142":["SG","535142","Tampines Road","","","","","","","1.362","103.8921",""],"535143":["SG","535143","Tampines Road","","","","","","","1.362","103.892",""],"535144":["SG","535144","Tampines Road","","","","","","","1.3622","103.8921",""],"535145":["SG","535145","Tampines Road","","","","","","","1.3622","103.8921",""],"535146":["SG","535146","Tampines Road","","","","","","","1.3622","103.892",""],"535147":["SG","535147","Tampines Road","","","","","","","1.3622","103.8919",""],"535148":["SG","535148","Tampines Road","","","","","","","1.3622","103.8919",""],"535149":["SG","535149","Tampines Road","","","","","","","1.3622","103.8918",""],"535150":["SG","535150","Tampines Road","","","","","","","1.3622","103.8918",""],"535151":["SG","535151","Tampines Road","","","","","","","1.3622","103.8917",""],"535152":["SG","535152","Tampines Road","","","","","","","1.3621","103.8917",""],"535153":["SG","535153","Tampines Road","","","","","","","1.3622","103.8924",""],"535154":["SG","535154","Tampines Road","","","","","","","1.3622","103.8924",""],"535155":["SG","535155","Tampines Road","","","","","","","1.3622","103.8925",""],"535156":["SG","535156","Tampines Road","","","","","","","1.3622","103.8926",""],"535157":["SG","535157","Tampines Road","","","","","","","1.3622","103.8926",""],"535158":["SG","535158","Tampines Road","","","","","","","1.3622","103.8927",""],"535159":["SG","535159","Tampines Road","","","","","","","1.362","103.8924",""],"535160":["SG","535160","Tampines Road","","","","","","","1.3618","103.8924",""],"535161":["SG","535161","Tampines Road","","","","","","","1.3618","103.8924",""],"535162":["SG","535162","Tampines Road","","","","","","","1.3618","103.8925",""],"535163":["SG","535163","Tampines Road","","","","","","","1.3618","103.8925",""],"535164":["SG","535164","Tampines Road","","","","","","","1.3618","103.8926",""],"535165":["SG","535165","Tampines Road","","","","","","","1.3618","103.8927",""],"535166":["SG","535166","Tampines Road","","","","","","","1.3619","103.8927",""],"535187":["SG","535187","Tampines Road","","","","","","","1.3608","103.8897",""],"535188":["SG","535188","Tampines Road","","","","","","","1.3609","103.8904",""],"535190":["SG","535190","Tampines Road","","","","","","","1.3608","103.8899",""],"535191":["SG","535191","Tampines Road","","","","","","","1.3753","103.9123",""],"535193":["SG","535193","Tampines Road","","","","","","","1.3607","103.892",""],"535194":["SG","535194","Taman Sireh","","","","","","","1.3534","103.8797",""],"535195":["SG","535195","Taman Sireh","","","","","","","1.3538","103.8794",""],"535196":["SG","535196","Taman Sireh","","","","","","","1.3534","103.8797",""],"535197":["SG","535197","Taman Sireh","","","","","","","1.3537","103.8793",""],"535198":["SG","535198","Taman Sireh","","","","","","","1.3534","103.8796",""],"535199":["SG","535199","Taman Sireh","","","","","","","1.3536","103.8792",""],"535200":["SG","535200","Taman Sireh","","","","","","","1.3533","103.8796",""],"535201":["SG","535201","Taman Sireh","","","","","","","1.3536","103.8792",""],"535202":["SG","535202","Taman Sireh","","","","","","","1.3533","103.8795",""],"535203":["SG","535203","Taman Sireh","","","","","","","1.3532","103.8795",""],"535204":["SG","535204","Taman Sireh","","","","","","","1.3532","103.8794",""],"535205":["SG","535205","Taman Sireh","","","","","","","1.3532","103.8794",""],"535206":["SG","535206","Taman Sireh","","","","","","","1.3531","103.8793",""],"535215":["SG","535215","Tai Seng Drive","","","","","","","1.3374","103.8924",""],"535216":["SG","535216","Tai Seng Drive","","","","","","","1.3378","103.8926",""],"535217":["SG","535217","Tai Seng Drive","","","","","","","1.3383","103.893",""],"535218":["SG","535218","Tai Seng Drive","","","","","","","1.3389","103.8929",""],"535219":["SG","535219","Tai Seng Drive","","","","","","","1.3382","103.8947",""],"535220":["SG","535220","Tai Seng Drive","","","","","","","1.3378","103.8952",""],"535221":["SG","535221","Tai Seng Drive","","","","","","","1.3375","103.8941",""],"535222":["SG","535222","Tai Seng Drive","","","","","","","1.3377","103.8937",""],"535223":["SG","535223","Tai Seng Drive","","","","","","","1.3374","103.8935",""],"535224":["SG","535224","Tai Seng Drive","","","","","","","1.337","103.8933",""],"535225":["SG","535225","Tai Seng Drive","","","","","","","1.3371","103.8946",""],"535226":["SG","535226","Tai Seng Drive","","","","","","","1.3385","103.8944",""],"535227":["SG","535227","Tai Seng Drive","","","","","","","1.3387","103.8939",""],"535233":["SG","535233","Tai Keng Terrace","","","","","","","1.3485","103.8853",""],"535234":["SG","535234","Tai Keng Terrace","","","","","","","1.3482","103.8852",""],"535235":["SG","535235","Tai Keng Terrace","","","","","","","1.3485","103.8854",""],"535236":["SG","535236","Tai Keng Terrace","","","","","","","1.3482","103.8852",""],"535237":["SG","535237","Tai Keng Terrace","","","","","","","1.3484","103.8854",""],"535238":["SG","535238","Tai Keng Terrace","","","","","","","1.3482","103.8853",""],"535239":["SG","535239","Tai Keng Terrace","","","","","","","1.3484","103.8855",""],"535240":["SG","535240","Tai Keng Terrace","","","","","","","1.3481","103.8853",""],"535241":["SG","535241","Tai Keng Terrace","","","","","","","1.3484","103.8855",""],"535242":["SG","535242","Tai Keng Terrace","","","","","","","1.3481","103.8854",""],"535243":["SG","535243","Tai Keng Terrace","","","","","","","1.3484","103.8856",""],"535244":["SG","535244","Tai Keng Terrace","","","","","","","1.3481","103.8854",""],"535245":["SG","535245","Tai Keng Terrace","","","","","","","1.3481","103.8855",""],"535246":["SG","535246","Tai Keng Terrace","","","","","","","1.3483","103.8856",""],"535247":["SG","535247","Tai Keng Terrace","","","","","","","1.348","103.8855",""],"535248":["SG","535248","Tai Keng Terrace","","","","","","","1.3483","103.8857",""],"535249":["SG","535249","Tai Keng Terrace","","","","","","","1.348","103.8856",""],"535250":["SG","535250","Tai Keng Terrace","","","","","","","1.3483","103.8857",""],"535251":["SG","535251","Tai Keng Terrace","","","","","","","1.348","103.8856",""],"535260":["SG","535260","Tai Keng Lane","","","","","","","1.3462","103.8841",""],"535261":["SG","535261","Tai Keng Lane","","","","","","","1.3462","103.8842",""],"535262":["SG","535262","Tai Keng Lane","","","","","","","1.3461","103.8842",""],"535263":["SG","535263","Tai Keng Lane","","","","","","","1.3461","103.8842",""],"535264":["SG","535264","Tai Keng Lane","","","","","","","1.346","103.8843",""],"535265":["SG","535265","Tai Keng Lane","","","","","","","1.346","103.8843",""],"535266":["SG","535266","Tai Keng Lane","","","","","","","1.3459","103.8844",""],"535267":["SG","535267","Tai Keng Lane","","","","","","","1.3458","103.8844",""],"535268":["SG","535268","Tai Keng Lane","","","","","","","1.3458","103.8845",""],"535269":["SG","535269","Tai Keng Lane","","","","","","","1.3458","103.8845",""],"535270":["SG","535270","Tai Keng Lane","","","","","","","1.3457","103.8846",""],"535271":["SG","535271","Tai Keng Lane","","","","","","","1.3457","103.8846",""],"535272":["SG","535272","Tai Keng Lane","","","","","","","1.3456","103.8846",""],"535273":["SG","535273","Tai Keng Lane","","","","","","","1.3456","103.8847",""],"535274":["SG","535274","Tai Keng Lane","","","","","","","1.3455","103.8847",""],"535283":["SG","535283","Tai Keng Gardens","","","","","","","1.3466","103.8834",""],"535284":["SG","535284","Tai Keng Gardens","","","","","","","1.3467","103.8838",""],"535285":["SG","535285","Tai Keng Gardens","","","","","","","1.3468","103.8835",""],"535286":["SG","535286","Tai Keng Gardens","","","","","","","1.3468","103.8838",""],"535287":["SG","535287","Tai Keng Gardens","","","","","","","1.3468","103.8835",""],"535288":["SG","535288","Tai Keng Gardens","","","","","","","1.3469","103.8838",""],"535289":["SG","535289","Tai Keng Gardens","","","","","","","1.347","103.8835",""],"535290":["SG","535290","Tai Keng Gardens","","","","","","","1.3469","103.8838",""],"535291":["SG","535291","Tai Keng Gardens","","","","","","","1.3471","103.8835",""],"535292":["SG","535292","Tai Keng Gardens","","","","","","","1.347","103.8839",""],"535293":["SG","535293","Tai Keng Gardens","","","","","","","1.3472","103.8836",""],"535294":["SG","535294","Tai Keng Gardens","","","","","","","1.347","103.8839",""],"535295":["SG","535295","Tai Keng Gardens","","","","","","","1.3471","103.8839",""],"535296":["SG","535296","Tai Keng Gardens","","","","","","","1.3473","103.8836",""],"535297":["SG","535297","Tai Keng Gardens","","","","","","","1.3471","103.8839",""],"535298":["SG","535298","Tai Keng Gardens","","","","","","","1.3474","103.8837",""],"535299":["SG","535299","Tai Keng Gardens","","","","","","","1.3473","103.884",""],"535300":["SG","535300","Tai Keng Gardens","","","","","","","1.3475","103.8837",""],"535301":["SG","535301","Tai Keng Gardens","","","","","","","1.3473","103.884",""],"535302":["SG","535302","Tai Keng Gardens","","","","","","","1.3476","103.8838",""],"535303":["SG","535303","Tai Keng Gardens","","","","","","","1.3474","103.884",""],"535304":["SG","535304","Tai Keng Gardens","","","","","","","1.3477","103.8838",""],"535305":["SG","535305","Tai Keng Gardens","","","","","","","1.3474","103.8841",""],"535306":["SG","535306","Tai Keng Gardens","","","","","","","1.3478","103.8839",""],"535307":["SG","535307","Tai Keng Gardens","","","","","","","1.3475","103.8841",""],"535308":["SG","535308","Tai Keng Gardens","","","","","","","1.3479","103.8839",""],"535309":["SG","535309","Tai Keng Gardens","","","","","","","1.3475","103.8841",""],"535310":["SG","535310","Tai Keng Gardens","","","","","","","1.348","103.884",""],"535311":["SG","535311","Tai Keng Gardens","","","","","","","1.3476","103.8841",""],"535312":["SG","535312","Tai Keng Gardens","","","","","","","1.3481","103.884",""],"535313":["SG","535313","Tai Keng Gardens","","","","","","","1.3476","103.8842",""],"535314":["SG","535314","Tai Keng Gardens","","","","","","","1.3482","103.8841",""],"535315":["SG","535315","Tai Keng Gardens","","","","","","","1.3478","103.8842",""],"535316":["SG","535316","Tai Keng Gardens","","","","","","","1.3483","103.8841",""],"535317":["SG","535317","Tai Keng Gardens","","","","","","","1.3478","103.8842",""],"535318":["SG","535318","Tai Keng Gardens","","","","","","","1.3484","103.8842",""],"535319":["SG","535319","Tai Keng Gardens","","","","","","","1.3479","103.8843",""],"535320":["SG","535320","Tai Keng Gardens","","","","","","","1.3485","103.8842",""],"535321":["SG","535321","Tai Keng Gardens","","","","","","","1.3479","103.8843",""],"535322":["SG","535322","Tai Keng Gardens","","","","","","","1.3486","103.8843",""],"535323":["SG","535323","Tai Keng Gardens","","","","","","","1.348","103.8843",""],"535324":["SG","535324","Tai Keng Gardens","","","","","","","1.3487","103.8843",""],"535325":["SG","535325","Tai Keng Gardens","","","","","","","1.348","103.8843",""],"535326":["SG","535326","Tai Keng Gardens","","","","","","","1.3488","103.8844",""],"535327":["SG","535327","Tai Keng Gardens","","","","","","","1.348","103.8845",""],"535328":["SG","535328","Tai Keng Gardens","","","","","","","1.3489","103.8844",""],"535329":["SG","535329","Tai Keng Gardens","","","","","","","1.3481","103.8844",""],"535330":["SG","535330","Tai Keng Gardens","","","","","","","1.349","103.8845",""],"535331":["SG","535331","Tai Keng Gardens","","","","","","","1.3482","103.8845",""],"535332":["SG","535332","Tai Keng Gardens","","","","","","","1.3491","103.8845",""],"535333":["SG","535333","Tai Keng Gardens","","","","","","","1.3483","103.8845",""],"535334":["SG","535334","Tai Keng Gardens","","","","","","","1.3491","103.8847",""],"535335":["SG","535335","Tai Keng Gardens","","","","","","","1.3483","103.8845",""],"535336":["SG","535336","Tai Keng Gardens","","","","","","","1.3492","103.8848",""],"535337":["SG","535337","Tai Keng Gardens","","","","","","","1.3484","103.8845",""],"535338":["SG","535338","Tai Keng Gardens","","","","","","","1.3491","103.8849",""],"535339":["SG","535339","Tai Keng Gardens","","","","","","","1.3484","103.8846",""],"535340":["SG","535340","Tai Keng Gardens","","","","","","","1.3492","103.885",""],"535341":["SG","535341","Tai Keng Gardens","","","","","","","1.3485","103.8846",""],"535342":["SG","535342","Tai Keng Gardens","","","","","","","1.3491","103.8854",""],"535343":["SG","535343","Tai Keng Gardens","","","","","","","1.3486","103.8846",""],"535344":["SG","535344","Tai Keng Gardens","","","","","","","1.3491","103.8854",""],"535345":["SG","535345","Tai Keng Gardens","","","","","","","1.3486","103.8847",""],"535346":["SG","535346","Tai Keng Gardens","","","","","","","1.349","103.8855",""],"535347":["SG","535347","Tai Keng Gardens","","","","","","","1.3488","103.8847",""],"535348":["SG","535348","Tai Keng Gardens","","","","","","","1.349","103.8855",""],"535349":["SG","535349","Tai Keng Gardens","","","","","","","1.3488","103.8853",""],"535350":["SG","535350","Tai Keng Gardens","","","","","","","1.349","103.8856",""],"535351":["SG","535351","Tai Keng Gardens","","","","","","","1.3487","103.8854",""],"535352":["SG","535352","Tai Keng Gardens","","","","","","","1.349","103.8856",""],"535353":["SG","535353","Tai Keng Gardens","","","","","","","1.3487","103.8854",""],"535354":["SG","535354","Tai Keng Gardens","","","","","","","1.3489","103.8857",""],"535355":["SG","535355","Tai Keng Gardens","","","","","","","1.3487","103.8855",""],"535356":["SG","535356","Tai Keng Gardens","","","","","","","1.3489","103.8858",""],"535357":["SG","535357","Tai Keng Gardens","","","","","","","1.3487","103.8856",""],"535358":["SG","535358","Tai Keng Gardens","","","","","","","1.3489","103.8858",""],"535359":["SG","535359","Tai Keng Gardens","","","","","","","1.3486","103.8856",""],"535360":["SG","535360","Tai Keng Gardens","","","","","","","1.3488","103.8859",""],"535361":["SG","535361","Tai Keng Gardens","","","","","","","1.3486","103.8857",""],"535362":["SG","535362","Tai Keng Gardens","","","","","","","1.3488","103.8859",""],"535363":["SG","535363","Tai Keng Gardens","","","","","","","1.3486","103.8857",""],"535364":["SG","535364","Tai Keng Gardens","","","","","","","1.3488","103.886",""],"535365":["SG","535365","Tai Keng Gardens","","","","","","","1.3485","103.8858",""],"535366":["SG","535366","Tai Keng Gardens","","","","","","","1.3488","103.886",""],"535367":["SG","535367","Tai Keng Gardens","","","","","","","1.3469","103.8859",""],"535368":["SG","535368","Tai Keng Gardens","","","","","","","1.3487","103.8861",""],"535369":["SG","535369","Tai Keng Gardens","","","","","","","1.347","103.8858",""],"535370":["SG","535370","Tai Keng Gardens","","","","","","","1.3487","103.8862",""],"535371":["SG","535371","Tai Keng Gardens","","","","","","","1.347","103.8858",""],"535372":["SG","535372","Tai Keng Gardens","","","","","","","1.3485","103.8861",""],"535373":["SG","535373","Tai Keng Gardens","","","","","","","1.3471","103.8857",""],"535374":["SG","535374","Tai Keng Gardens","","","","","","","1.3484","103.886",""],"535375":["SG","535375","Tai Keng Gardens","","","","","","","1.347","103.8857",""],"535376":["SG","535376","Tai Keng Gardens","","","","","","","1.3484","103.886",""],"535377":["SG","535377","Tai Keng Gardens","","","","","","","1.3471","103.8856",""],"535378":["SG","535378","Tai Keng Gardens","","","","","","","1.3483","103.886",""],"535379":["SG","535379","Tai Keng Gardens","","","","","","","1.3471","103.8855",""],"535380":["SG","535380","Tai Keng Gardens","","","","","","","1.3482","103.886",""],"535381":["SG","535381","Tai Keng Gardens","","","","","","","1.3471","103.8855",""],"535382":["SG","535382","Tai Keng Gardens","","","","","","","1.3482","103.886",""],"535383":["SG","535383","Tai Keng Gardens","","","","","","","1.3472","103.8854",""],"535384":["SG","535384","Tai Keng Gardens","","","","","","","1.3481","103.886",""],"535385":["SG","535385","Tai Keng Gardens","","","","","","","1.3472","103.8854",""],"535386":["SG","535386","Tai Keng Gardens","","","","","","","1.3481","103.8859",""],"535387":["SG","535387","Tai Keng Gardens","","","","","","","1.3472","103.8853",""],"535388":["SG","535388","Tai Keng Gardens","","","","","","","1.348","103.8859",""],"535389":["SG","535389","Tai Keng Gardens","","","","","","","1.3473","103.8852",""],"535390":["SG","535390","Tai Keng Gardens","","","","","","","1.3479","103.8859",""],"535391":["SG","535391","Tai Keng Gardens","","","","","","","1.3473","103.8852",""],"535392":["SG","535392","Tai Keng Gardens","","","","","","","1.3478","103.8859",""],"535393":["SG","535393","Tai Keng Gardens","","","","","","","1.3473","103.8851",""],"535394":["SG","535394","Tai Keng Gardens","","","","","","","1.3477","103.8859",""],"535395":["SG","535395","Tai Keng Gardens","","","","","","","1.3473","103.8851",""],"535396":["SG","535396","Tai Keng Gardens","","","","","","","1.3477","103.886",""],"535397":["SG","535397","Tai Keng Gardens","","","","","","","1.3474","103.885",""],"535398":["SG","535398","Tai Keng Gardens","","","","","","","1.3476","103.886",""],"535399":["SG","535399","Tai Keng Gardens","","","","","","","1.3474","103.885",""],"535400":["SG","535400","Tai Keng Gardens","","","","","","","1.3476","103.886",""],"535401":["SG","535401","Tai Keng Gardens","","","","","","","1.347","103.8848",""],"535402":["SG","535402","Tai Keng Gardens","","","","","","","1.3475","103.886",""],"535403":["SG","535403","Tai Keng Gardens","","","","","","","1.347","103.8849",""],"535404":["SG","535404","Tai Keng Gardens","","","","","","","1.3475","103.8861",""],"535405":["SG","535405","Tai Keng Gardens","","","","","","","1.347","103.8849",""],"535406":["SG","535406","Tai Keng Gardens","","","","","","","1.3474","103.8861",""],"535407":["SG","535407","Tai Keng Gardens","","","","","","","1.347","103.885",""],"535408":["SG","535408","Tai Keng Gardens","","","","","","","1.3473","103.8861",""],"535409":["SG","535409","Tai Keng Gardens","","","","","","","1.347","103.885",""],"535410":["SG","535410","Tai Keng Gardens","","","","","","","1.3473","103.8862",""],"535411":["SG","535411","Tai Keng Gardens","","","","","","","1.347","103.8851",""],"535412":["SG","535412","Tai Keng Gardens","","","","","","","1.3472","103.8862",""],"535413":["SG","535413","Tai Keng Gardens","","","","","","","1.3469","103.8852",""],"535414":["SG","535414","Tai Keng Gardens","","","","","","","1.3471","103.8862",""],"535415":["SG","535415","Tai Keng Gardens","","","","","","","1.3469","103.8852",""],"535416":["SG","535416","Tai Keng Gardens","","","","","","","1.3471","103.8862",""],"535417":["SG","535417","Tai Keng Gardens","","","","","","","1.3469","103.8853",""],"535418":["SG","535418","Tai Keng Gardens","","","","","","","1.347","103.8862",""],"535419":["SG","535419","Tai Keng Gardens","","","","","","","1.3468","103.8854",""],"535420":["SG","535420","Tai Keng Gardens","","","","","","","1.347","103.8862",""],"535421":["SG","535421","Tai Keng Gardens","","","","","","","1.3468","103.8854",""],"535422":["SG","535422","Tai Keng Gardens","","","","","","","1.3469","103.8862",""],"535423":["SG","535423","Tai Keng Gardens","","","","","","","1.3468","103.8855",""],"535424":["SG","535424","Tai Keng Gardens","","","","","","","1.3468","103.8855",""],"535425":["SG","535425","Tai Keng Gardens","","","","","","","1.3467","103.8856",""],"535426":["SG","535426","Tai Keng Gardens","","","","","","","1.3467","103.8856",""],"535427":["SG","535427","Tai Keng Gardens","","","","","","","1.3467","103.8857",""],"535428":["SG","535428","Tai Keng Gardens","","","","","","","1.3467","103.8858",""],"535429":["SG","535429","Tai Keng Gardens","","","","","","","1.3466","103.8858",""],"535430":["SG","535430","Tai Keng Gardens","","","","","","","1.3466","103.8859",""],"535431":["SG","535431","Tai Keng Gardens","","","","","","","1.3464","103.8858",""],"535432":["SG","535432","Tai Keng Gardens","","","","","","","1.3465","103.8858",""],"535433":["SG","535433","Tai Keng Gardens","","","","","","","1.3462","103.8861",""],"535434":["SG","535434","Tai Keng Gardens","","","","","","","1.3464","103.8857",""],"535435":["SG","535435","Tai Keng Gardens","","","","","","","1.3461","103.8861",""],"535436":["SG","535436","Tai Keng Gardens","","","","","","","1.3464","103.8856",""],"535437":["SG","535437","Tai Keng Gardens","","","","","","","1.346","103.886",""],"535438":["SG","535438","Tai Keng Gardens","","","","","","","1.3465","103.8856",""],"535439":["SG","535439","Tai Keng Gardens","","","","","","","1.346","103.886",""],"535440":["SG","535440","Tai Keng Gardens","","","","","","","1.3465","103.8855",""],"535441":["SG","535441","Tai Keng Gardens","","","","","","","1.3465","103.8855",""],"535442":["SG","535442","Tai Keng Gardens","","","","","","","1.3466","103.8853",""],"535443":["SG","535443","Tai Keng Gardens","","","","","","","1.3466","103.8853",""],"535444":["SG","535444","Tai Keng Gardens","","","","","","","1.3466","103.8852",""],"535445":["SG","535445","Tai Keng Gardens","","","","","","","1.3466","103.8852",""],"535446":["SG","535446","Tai Keng Gardens","","","","","","","1.3467","103.8851",""],"535447":["SG","535447","Tai Keng Gardens","","","","","","","1.3467","103.8851",""],"535448":["SG","535448","Tai Keng Gardens","","","","","","","1.3467","103.885",""],"535449":["SG","535449","Tai Keng Gardens","","","","","","","1.3467","103.885",""],"535450":["SG","535450","Tai Keng Gardens","","","","","","","1.3454","103.8845",""],"535451":["SG","535451","Tai Keng Gardens","","","","","","","1.3454","103.8845",""],"535452":["SG","535452","Tai Keng Gardens","","","","","","","1.3455","103.8844",""],"535453":["SG","535453","Tai Keng Gardens","","","","","","","1.3455","103.8844",""],"535454":["SG","535454","Tai Keng Gardens","","","","","","","1.3455","103.8843",""],"535455":["SG","535455","Tai Keng Gardens","","","","","","","1.3456","103.8843",""],"535456":["SG","535456","Tai Keng Gardens","","","","","","","1.3456","103.8843",""],"535457":["SG","535457","Tai Keng Gardens","","","","","","","1.3457","103.8842",""],"535458":["SG","535458","Tai Keng Gardens","","","","","","","1.3453","103.884",""],"535459":["SG","535459","Tai Keng Gardens","","","","","","","1.3458","103.8841",""],"535460":["SG","535460","Tai Keng Gardens","","","","","","","1.3454","103.884",""],"535461":["SG","535461","Tai Keng Gardens","","","","","","","1.3458","103.8841",""],"535462":["SG","535462","Tai Keng Gardens","","","","","","","1.3455","103.884",""],"535463":["SG","535463","Tai Keng Gardens","","","","","","","1.3459","103.8841",""],"535464":["SG","535464","Tai Keng Gardens","","","","","","","1.3459","103.884",""],"535465":["SG","535465","Tai Keng Gardens","","","","","","","1.3459","103.884",""],"535466":["SG","535466","Tai Keng Gardens","","","","","","","1.346","103.8839",""],"535467":["SG","535467","Tai Keng Gardens","","","","","","","1.346","103.8839",""],"535468":["SG","535468","Tai Keng Gardens","","","","","","","1.3461","103.8839",""],"535469":["SG","535469","Tai Keng Gardens","","","","","","","1.3461","103.8838",""],"535470":["SG","535470","Tai Keng Gardens","","","","","","","1.3452","103.8843",""],"535471":["SG","535471","Tai Keng Gardens","","","","","","","1.3452","103.8842",""],"535472":["SG","535472","Tai Keng Gardens","","","","","","","1.3451","103.8842",""],"535473":["SG","535473","Tai Keng Gardens","","","","","","","1.3451","103.8841",""],"535474":["SG","535474","Tai Keng Gardens","","","","","","","1.3451","103.8841",""],"535475":["SG","535475","Tai Keng Gardens","","","","","","","1.345","103.8841",""],"535476":["SG","535476","Tai Keng Gardens","","","","","","","1.345","103.884",""],"535477":["SG","535477","Tai Keng Gardens","","","","","","","1.3457","103.8855",""],"535478":["SG","535478","Tai Keng Gardens","","","","","","","1.3457","103.8855",""],"535479":["SG","535479","Tai Keng Gardens","","","","","","","1.3457","103.8854",""],"535480":["SG","535480","Tai Keng Gardens","","","","","","","1.3456","103.8854",""],"535481":["SG","535481","Tai Keng Gardens","","","","","","","1.3456","103.8853",""],"535482":["SG","535482","Tai Keng Gardens","","","","","","","1.3456","103.8853",""],"535483":["SG","535483","Tai Keng Gardens","","","","","","","1.3455","103.8852",""],"535484":["SG","535484","Tai Keng Gardens","","","","","","","1.3455","103.8852",""],"535485":["SG","535485","Tai Keng Avenue","","","","","","","1.348","103.8851",""],"535486":["SG","535486","Tai Keng Avenue","","","","","","","1.3476","103.8851",""],"535487":["SG","535487","Tai Keng Avenue","","","","","","","1.348","103.8851",""],"535488":["SG","535488","Tai Keng Avenue","","","","","","","1.3476","103.8851",""],"535489":["SG","535489","Tai Keng Avenue","","","","","","","1.3479","103.8852",""],"535490":["SG","535490","Tai Keng Avenue","","","","","","","1.3475","103.8852",""],"535491":["SG","535491","Tai Keng Avenue","","","","","","","1.3479","103.8852",""],"535492":["SG","535492","Tai Keng Avenue","","","","","","","1.3475","103.8852",""],"535493":["SG","535493","Tai Keng Avenue","","","","","","","1.3479","103.8853",""],"535494":["SG","535494","Tai Keng Avenue","","","","","","","1.3475","103.8853",""],"535495":["SG","535495","Tai Keng Avenue","","","","","","","1.3479","103.8853",""],"535496":["SG","535496","Tai Keng Avenue","","","","","","","1.3475","103.8854",""],"535498":["SG","535498","Tai Keng Avenue","","","","","","","1.3474","103.8854",""],"535499":["SG","535499","Tai Keng Avenue","","","","","","","1.3478","103.8854",""],"535500":["SG","535500","Tai Keng Avenue","","","","","","","1.3474","103.8855",""],"535501":["SG","535501","Tai Keng Avenue","","","","","","","1.3478","103.8855",""],"535502":["SG","535502","Tai Keng Avenue","","","","","","","1.3474","103.8856",""],"535503":["SG","535503","Tai Keng Avenue","","","","","","","1.3478","103.8855",""],"535504":["SG","535504","Tai Keng Avenue","","","","","","","1.3474","103.8856",""],"535505":["SG","535505","Tai Keng Avenue","","","","","","","1.3477","103.8856",""],"535506":["SG","535506","Tai Keng Avenue","","","","","","","1.3473","103.8857",""],"535507":["SG","535507","Tai Keng Avenue","","","","","","","1.3477","103.8856",""],"535508":["SG","535508","Tai Keng Avenue","","","","","","","1.3473","103.8857",""],"535509":["SG","535509","Tai Keng Avenue","","","","","","","1.3473","103.8858",""],"535510":["SG","535510","Tai Keng Avenue","","","","","","","1.3473","103.8858",""],"535511":["SG","535511","Tai Keng Avenue","","","","","","","1.3472","103.8859",""],"535519":["SG","535519","Surin Road","","","","","","","1.3555","103.8804",""],"535520":["SG","535520","Surin Road","","","","","","","1.3554","103.8802",""],"535521":["SG","535521","Surin Road","","","","","","","1.3555","103.8805",""],"535522":["SG","535522","Surin Road","","","","","","","1.3553","103.8803",""],"535523":["SG","535523","Surin Road","","","","","","","1.3554","103.8806",""],"535524":["SG","535524","Surin Road","","","","","","","1.3551","103.8804",""],"535525":["SG","535525","Surin Road","","","","","","","1.3553","103.8807",""],"535526":["SG","535526","Surin Road","","","","","","","1.3551","103.8805",""],"535527":["SG","535527","Surin Road","","","","","","","1.3552","103.8808",""],"535528":["SG","535528","Surin Road","","","","","","","1.3549","103.8806",""],"535529":["SG","535529","Surin Road","","","","","","","1.3551","103.8809",""],"535530":["SG","535530","Surin Road","","","","","","","1.3549","103.8807",""],"535531":["SG","535531","Surin Road","","","","","","","1.3548","103.8808",""],"535532":["SG","535532","Surin Road","","","","","","","1.3549","103.881",""],"535533":["SG","535533","Surin Road","","","","","","","1.3549","103.881",""],"535534":["SG","535534","Surin Road","","","","","","","1.355","103.881",""],"535542":["SG","535542","Surin Lane","","","","","","","1.3546","103.881",""],"535543":["SG","535543","Surin Lane","","","","","","","1.3548","103.8814",""],"535545":["SG","535545","Surin Lane","","","","","","","1.3544","103.881",""],"535546":["SG","535546","Surin Lane","","","","","","","1.3547","103.8813",""],"535547":["SG","535547","Surin Lane","","","","","","","1.3543","103.881",""],"535548":["SG","535548","Surin Lane","","","","","","","1.3545","103.8814",""],"535549":["SG","535549","Surin Lane","","","","","","","1.3541","103.881",""],"535550":["SG","535550","Surin Lane","","","","","","","1.3542","103.8814",""],"535551":["SG","535551","Surin Lane","","","","","","","1.3541","103.8815",""],"535552":["SG","535552","Surin Lane","","","","","","","1.354","103.8814",""],"535553":["SG","535553","Surin Lane","","","","","","","1.3539","103.8814",""],"535554":["SG","535554","Surin Lane","","","","","","","1.354","103.881",""],"535555":["SG","535555","Surin Lane","","","","","","","1.3538","103.8814",""],"535556":["SG","535556","Surin Lane","","","","","","","1.3539","103.881",""],"535557":["SG","535557","Surin Lane","","","","","","","1.3538","103.881",""],"535558":["SG","535558","Surin Lane","","","","","","","1.3536","103.8814",""],"535559":["SG","535559","Surin Lane","","","","","","","1.3535","103.8815",""],"535560":["SG","535560","Surin Lane","","","","","","","1.3536","103.8811",""],"535561":["SG","535561","Surin Lane","","","","","","","1.3533","103.8814",""],"535562":["SG","535562","Surin Lane","","","","","","","1.3536","103.8811",""],"535563":["SG","535563","Surin Lane","","","","","","","1.3533","103.8814",""],"535564":["SG","535564","Surin Lane","","","","","","","1.3535","103.8811",""],"535565":["SG","535565","Surin Lane","","","","","","","1.3534","103.8811",""],"535566":["SG","535566","Surin Lane","","","","","","","1.3533","103.8811",""],"535567":["SG","535567","Surin Lane","","","","","","","1.3533","103.8811",""],"535569":["SG","535569","Surin Lane","","","","","","","1.3536","103.8811",""],"535570":["SG","535570","Surin Lane","","","","","","","1.3535","103.8811",""],"535571":["SG","535571","Surin Lane","","","","","","","1.3534","103.8811",""],"535572":["SG","535572","Surin Lane","","","","","","","1.3542","103.8809",""],"535573":["SG","535573","Surin Lane","","","","","","","1.3537","103.8814",""],"535576":["SG","535576","Surin Avenue","","","","","","","1.3543","103.8797",""],"535577":["SG","535577","Surin Avenue","","","","","","","1.3539","103.8796",""],"535578":["SG","535578","Surin Avenue","","","","","","","1.3539","103.8797",""],"535579":["SG","535579","Surin Avenue","","","","","","","1.3539","103.8797",""],"535580":["SG","535580","Surin Avenue","","","","","","","1.354","103.8798",""],"535581":["SG","535581","Surin Avenue","","","","","","","1.354","103.8799",""],"535582":["SG","535582","Surin Avenue","","","","","","","1.354","103.8799",""],"535583":["SG","535583","Surin Avenue","","","","","","","1.3542","103.8803",""],"535584":["SG","535584","Surin Avenue","","","","","","","1.3544","103.8801",""],"535585":["SG","535585","Surin Avenue","","","","","","","1.3543","103.8804",""],"535586":["SG","535586","Surin Avenue","","","","","","","1.355","103.8801",""],"535587":["SG","535587","Surin Avenue","","","","","","","1.355","103.8802",""],"535588":["SG","535588","Surin Avenue","","","","","","","1.3543","103.8804",""],"535589":["SG","535589","Surin Avenue","","","","","","","1.3549","103.8802",""],"535590":["SG","535590","Surin Avenue","","","","","","","1.3549","103.8802",""],"535591":["SG","535591","Surin Avenue","","","","","","","1.3543","103.8805",""],"535592":["SG","535592","Surin Avenue","","","","","","","1.3548","103.8803",""],"535593":["SG","535593","Surin Avenue","","","","","","","1.3547","103.8803",""],"535594":["SG","535594","Surin Avenue","","","","","","","1.3543","103.8805",""],"535595":["SG","535595","Surin Avenue","","","","","","","1.3547","103.8804",""],"535596":["SG","535596","Surin Avenue","","","","","","","1.3547","103.8804",""],"535597":["SG","535597","Surin Avenue","","","","","","","1.3544","103.8806",""],"535598":["SG","535598","Surin Avenue","","","","","","","1.3548","103.8805",""],"535599":["SG","535599","Surin Avenue","","","","","","","1.3548","103.8805",""],"535600":["SG","535600","Surin Avenue","","","","","","","1.3544","103.8807",""],"535601":["SG","535601","Surin Avenue","","","","","","","1.3544","103.8807",""],"535603":["SG","535603","Surin Avenue","","","","","","","1.355","103.8812",""],"535604":["SG","535604","Surin Avenue","","","","","","","1.3551","103.8811",""],"535605":["SG","535605","Surin Avenue","","","","","","","1.3553","103.8809",""],"535606":["SG","535606","Surin Avenue","","","","","","","1.3553","103.8809",""],"535607":["SG","535607","Surin Avenue","","","","","","","1.3554","103.8808",""],"535608":["SG","535608","Surin Avenue","","","","","","","1.3556","103.8809",""],"535609":["SG","535609","Surin Avenue","","","","","","","1.3556","103.881",""],"535610":["SG","535610","Surin Avenue","","","","","","","1.3555","103.881",""],"535611":["SG","535611","Surin Avenue","","","","","","","1.355","103.8819",""],"535612":["SG","535612","Surin Avenue","","","","","","","1.3553","103.8812",""],"535613":["SG","535613","Surin Avenue","","","","","","","1.3553","103.8812",""],"535614":["SG","535614","Surin Avenue","","","","","","","1.3552","103.8812",""],"535615":["SG","535615","Surin Avenue","","","","","","","1.3551","103.882",""],"535616":["SG","535616","Surin Avenue","","","","","","","1.3554","103.8818",""],"535620":["SG","535620","Surin Avenue","","","","","","","1.3552","103.8816",""],"535621":["SG","535621","Surin Avenue","","","","","","","1.3553","103.8817",""],"535622":["SG","535622","Surin Avenue","","","","","","","1.3553","103.8818",""],"535623":["SG","535623","Surin Avenue","","","","","","","1.3553","103.8818",""],"535624":["SG","535624","Surin Avenue","","","","","","","1.3552","103.8822",""],"535625":["SG","535625","Surin Avenue","","","","","","","1.3554","103.8819",""],"535626":["SG","535626","Surin Avenue","","","","","","","1.3552","103.8822",""],"535627":["SG","535627","Surin Avenue","","","","","","","1.3555","103.882",""],"535628":["SG","535628","Surin Avenue","","","","","","","1.3555","103.882",""],"535629":["SG","535629","Surin Avenue","","","","","","","1.3555","103.8821",""],"535630":["SG","535630","Surin Avenue","","","","","","","1.3553","103.8824",""],"535631":["SG","535631","Surin Avenue","","","","","","","1.3556","103.8821",""],"535632":["SG","535632","Surin Avenue","","","","","","","1.3556","103.8822",""],"535633":["SG","535633","Surin Avenue","","","","","","","1.3556","103.8822",""],"535634":["SG","535634","Surin Avenue","","","","","","","1.3553","103.8825",""],"535635":["SG","535635","Surin Avenue","","","","","","","1.3557","103.8822",""],"535636":["SG","535636","Surin Avenue","","","","","","","1.3557","103.8823",""],"535637":["SG","535637","Surin Avenue","","","","","","","1.3558","103.8823",""],"535638":["SG","535638","Surin Avenue","","","","","","","1.3554","103.8829",""],"535639":["SG","535639","Surin Avenue","","","","","","","1.3557","103.8825",""],"535640":["SG","535640","Surin Avenue","","","","","","","1.3557","103.8826",""],"535641":["SG","535641","Surin Avenue","","","","","","","1.3558","103.8826",""],"535642":["SG","535642","Surin Avenue","","","","","","","1.3558","103.8827",""],"535643":["SG","535643","Surin Avenue","","","","","","","1.3558","103.8827",""],"535644":["SG","535644","Surin Avenue","","","","","","","1.3559","103.8828",""],"535645":["SG","535645","Surin Avenue","","","","","","","1.3559","103.8828",""],"535646":["SG","535646","Surin Avenue","","","","","","","1.3559","103.8829",""],"535647":["SG","535647","Surin Avenue","","","","","","","1.356","103.8829",""],"535648":["SG","535648","Surin Avenue","","","","","","","1.356","103.883",""],"535649":["SG","535649","Surin Avenue","","","","","","","1.356","103.8831",""],"535650":["SG","535650","Surin Avenue","","","","","","","1.3562","103.8832",""],"535651":["SG","535651","Surin Avenue","","","","","","","1.3563","103.8845",""],"535652":["SG","535652","Surin Avenue","","","","","","","1.3563","103.8846",""],"535653":["SG","535653","Surin Avenue","","","","","","","1.3564","103.8847",""],"535654":["SG","535654","Surin Avenue","","","","","","","1.3564","103.8848",""],"535655":["SG","535655","Surin Avenue","","","","","","","1.3565","103.8849",""],"535656":["SG","535656","Surin Avenue","","","","","","","1.3566","103.8852",""],"535657":["SG","535657","Surin Avenue","","","","","","","1.3566","103.8853",""],"535658":["SG","535658","Surin Avenue","","","","","","","1.3566","103.8854",""],"535659":["SG","535659","Surin Avenue","","","","","","","1.3566","103.8854",""],"535660":["SG","535660","Surin Avenue","","","","","","","1.3567","103.8856",""],"535661":["SG","535661","Surin Avenue","","","","","","","1.3567","103.8856",""],"535662":["SG","535662","Surin Avenue","","","","","","","1.3568","103.8857",""],"535663":["SG","535663","Surin Avenue","","","","","","","1.3568","103.8858",""],"535664":["SG","535664","Surin Avenue","","","","","","","1.3569","103.8859",""],"535665":["SG","535665","Surin Avenue","","","","","","","1.3569","103.886",""],"535666":["SG","535666","Surin Avenue","","","","","","","1.357","103.8861",""],"535667":["SG","535667","Surin Avenue","","","","","","","1.357","103.8861",""],"535668":["SG","535668","Surin Avenue","","","","","","","1.3571","103.8863",""],"535669":["SG","535669","Surin Avenue","","","","","","","1.3572","103.8864",""],"535670":["SG","535670","Surin Avenue","","","","","","","1.3572","103.8865",""],"535671":["SG","535671","Surin Avenue","","","","","","","1.3572","103.8866",""],"535672":["SG","535672","Surin Avenue","","","","","","","1.3573","103.8867",""],"535673":["SG","535673","Surin Avenue","","","","","","","1.3573","103.8867",""],"535674":["SG","535674","Surin Avenue","","","","","","","1.3574","103.8869",""],"535675":["SG","535675","Surin Avenue","","","","","","","1.3574","103.8869",""],"535676":["SG","535676","Surin Avenue","","","","","","","1.3575","103.887",""],"535677":["SG","535677","Surin Avenue","","","","","","","1.3575","103.8871",""],"535678":["SG","535678","Surin Avenue","","","","","","","1.3576","103.8872",""],"535679":["SG","535679","Surin Avenue","","","","","","","1.3576","103.8873",""],"535681":["SG","535681","Surin Avenue","","","","","","","1.3565","103.885",""],"535682":["SG","535682","Surin Avenue","","","","","","","1.3549","103.8815",""],"535683":["SG","535683","Surin Avenue","","","","","","","1.3561","103.8831",""],"535684":["SG","535684","Surin Avenue","","","","","","","1.3577","103.8874",""],"535685":["SG","535685","Surin Avenue","","","","","","","1.3577","103.8875",""],"535686":["SG","535686","Surin Avenue","","","","","","","1.3577","103.8875",""],"535687":["SG","535687","Surin Avenue","","","","","","","1.3578","103.8876",""],"535688":["SG","535688","Surin Avenue","","","","","","","1.3578","103.8876",""],"535689":["SG","535689","Sunshine Terrace","","","","","","","1.3462","103.872",""],"535690":["SG","535690","Sunshine Terrace","","","","","","","1.3456","103.8721",""],"535691":["SG","535691","Sunshine Terrace","","","","","","","1.3456","103.8722",""],"535692":["SG","535692","Sunshine Terrace","","","","","","","1.3456","103.8722",""],"535693":["SG","535693","Sunshine Terrace","","","","","","","1.3455","103.8723",""],"535694":["SG","535694","Sunshine Terrace","","","","","","","1.3455","103.8723",""],"535695":["SG","535695","Sunshine Terrace","","","","","","","1.3452","103.8724",""],"535696":["SG","535696","Sunshine Terrace","","","","","","","1.3452","103.8725",""],"535697":["SG","535697","Sunshine Terrace","","","","","","","1.3453","103.8726",""],"535698":["SG","535698","Sunshine Terrace","","","","","","","1.3453","103.8726",""],"535699":["SG","535699","Sunshine Terrace","","","","","","","1.3454","103.8726",""],"535700":["SG","535700","Sunshine Terrace","","","","","","","1.3455","103.8726",""],"535701":["SG","535701","Sunshine Terrace","","","","","","","1.3455","103.8726",""],"535702":["SG","535702","Sunshine Terrace","","","","","","","1.3455","103.8727",""],"535703":["SG","535703","Sunshine Terrace","","","","","","","1.3455","103.8727",""],"535704":["SG","535704","Sunshine Terrace","","","","","","","1.3455","103.8728",""],"535705":["SG","535705","Sunshine Terrace","","","","","","","1.3455","103.8729",""],"535706":["SG","535706","Sunshine Terrace","","","","","","","1.3454","103.8729",""],"535707":["SG","535707","Sunshine Terrace","","","","","","","1.3453","103.8731",""],"535708":["SG","535708","Sunshine Terrace","","","","","","","1.3456","103.8733",""],"535709":["SG","535709","Sunshine Terrace","","","","","","","1.3453","103.8733",""],"535710":["SG","535710","Sunshine Terrace","","","","","","","1.3456","103.8734",""],"535711":["SG","535711","Sunshine Terrace","","","","","","","1.3456","103.8735",""],"535712":["SG","535712","Sunshine Terrace","","","","","","","1.3456","103.8735",""],"535713":["SG","535713","Sunshine Terrace","","","","","","","1.3456","103.8736",""],"535714":["SG","535714","Sunshine Terrace","","","","","","","1.3456","103.8737",""],"535715":["SG","535715","Sunshine Terrace","","","","","","","1.3456","103.8737",""],"535716":["SG","535716","Sunshine Terrace","","","","","","","1.3456","103.8738",""],"535717":["SG","535717","Sunshine Terrace","","","","","","","1.3456","103.8739",""],"535718":["SG","535718","Sunshine Terrace","","","","","","","1.3456","103.8739",""],"535719":["SG","535719","Sunshine Terrace","","","","","","","1.3456","103.874",""],"535720":["SG","535720","Sunshine Terrace","","","","","","","1.3453","103.8734",""],"535721":["SG","535721","Sunshine Terrace","","","","","","","1.3454","103.873",""],"535722":["SG","535722","Sunshine Terrace","","","","","","","1.3453","103.8732",""],"535728":["SG","535728","Saint Xavier'S Lane","","","","","","","1.3717","103.898",""],"535729":["SG","535729","Saint Xavier'S Lane","","","","","","","1.3716","103.898",""],"535730":["SG","535730","Saint Xavier'S Lane","","","","","","","1.3716","103.898",""],"535731":["SG","535731","Saint Xavier'S Lane","","","","","","","1.3715","103.8981",""],"535732":["SG","535732","Saint Xavier'S Lane","","","","","","","1.3715","103.8981",""],"535733":["SG","535733","Saint Xavier'S Lane","","","","","","","1.3714","103.8981",""],"535734":["SG","535734","Saint Xavier'S Lane","","","","","","","1.3714","103.8982",""],"535735":["SG","535735","Saint Xavier'S Lane","","","","","","","1.3713","103.8982",""],"535736":["SG","535736","Saint Xavier'S Lane","","","","","","","1.3712","103.8983",""],"535737":["SG","535737","Saint Xavier'S Lane","","","","","","","1.3711","103.8984",""],"535738":["SG","535738","Saint Xavier'S Lane","","","","","","","1.3711","103.8984",""],"535739":["SG","535739","Upper Serangoon Road","","","","","","","1.3719","103.8978",""],"535740":["SG","535740","Upper Serangoon Road","","","","","","","1.3718","103.8979",""],"535746":["SG","535746","Serangoon Terrace","","","","","","","1.3478","103.877",""],"535747":["SG","535747","Serangoon Terrace","","","","","","","1.3478","103.8773",""],"535748":["SG","535748","Serangoon Terrace","","","","","","","1.3478","103.877",""],"535749":["SG","535749","Serangoon Terrace","","","","","","","1.3479","103.8773",""],"535750":["SG","535750","Serangoon Terrace","","","","","","","1.3479","103.877",""],"535751":["SG","535751","Serangoon Terrace","","","","","","","1.3479","103.8774",""],"535752":["SG","535752","Serangoon Terrace","","","","","","","1.3479","103.877",""],"535753":["SG","535753","Serangoon Terrace","","","","","","","1.3479","103.8774",""],"535754":["SG","535754","Serangoon Terrace","","","","","","","1.348","103.877",""],"535755":["SG","535755","Serangoon Terrace","","","","","","","1.348","103.8775",""],"535756":["SG","535756","Serangoon Terrace","","","","","","","1.348","103.877",""],"535757":["SG","535757","Serangoon Terrace","","","","","","","1.3478","103.8775",""],"535758":["SG","535758","Serangoon Terrace","","","","","","","1.3481","103.877",""],"535759":["SG","535759","Serangoon Terrace","","","","","","","1.3478","103.8775",""],"535760":["SG","535760","Serangoon Terrace","","","","","","","1.3482","103.877",""],"535761":["SG","535761","Serangoon Terrace","","","","","","","1.3477","103.8775",""],"535762":["SG","535762","Serangoon Terrace","","","","","","","1.3482","103.877",""],"535763":["SG","535763","Serangoon Terrace","","","","","","","1.3477","103.8776",""],"535764":["SG","535764","Serangoon Terrace","","","","","","","1.3483","103.8776",""],"535765":["SG","535765","Serangoon Terrace","","","","","","","1.3476","103.8775",""],"535766":["SG","535766","Serangoon Terrace","","","","","","","1.3483","103.8776",""],"535767":["SG","535767","Serangoon Terrace","","","","","","","1.3475","103.8775",""],"535768":["SG","535768","Serangoon Terrace","","","","","","","1.3482","103.8776",""],"535769":["SG","535769","Serangoon Terrace","","","","","","","1.3475","103.8776",""],"535770":["SG","535770","Serangoon Terrace","","","","","","","1.3482","103.8776",""],"535771":["SG","535771","Serangoon Terrace","","","","","","","1.3475","103.8776",""],"535772":["SG","535772","Serangoon Terrace","","","","","","","1.3481","103.8777",""],"535773":["SG","535773","Serangoon Terrace","","","","","","","1.3474","103.8777",""],"535774":["SG","535774","Serangoon Terrace","","","","","","","1.3481","103.8777",""],"535775":["SG","535775","Serangoon Terrace","","","","","","","1.3474","103.8777",""],"535776":["SG","535776","Serangoon Terrace","","","","","","","1.348","103.8777",""],"535777":["SG","535777","Serangoon Terrace","","","","","","","1.348","103.8778",""],"535778":["SG","535778","Serangoon Terrace","","","","","","","1.3479","103.8778",""],"535779":["SG","535779","Serangoon Terrace","","","","","","","1.3479","103.8779",""],"535780":["SG","535780","Serangoon Terrace","","","","","","","1.3478","103.8779",""],"535781":["SG","535781","Serangoon Terrace","","","","","","","1.3478","103.8779",""],"535782":["SG","535782","Serangoon Terrace","","","","","","","1.3477","103.8779",""],"535783":["SG","535783","Serangoon Terrace","","","","","","","1.3477","103.878",""],"535784":["SG","535784","Serangoon Terrace","","","","","","","1.3476","103.878",""],"535785":["SG","535785","Serangoon Terrace","","","","","","","1.3476","103.878",""],"535786":["SG","535786","Serangoon Terrace","","","","","","","1.3475","103.878",""],"535787":["SG","535787","Serangoon Terrace","","","","","","","1.3475","103.8781",""],"535788":["SG","535788","Serangoon Terrace","","","","","","","1.3475","103.8781",""],"535797":["SG","535797","Serangoon Lane","","","","","","","1.3463","103.8778",""],"535798":["SG","535798","Serangoon Lane","","","","","","","1.3459","103.8778",""],"535799":["SG","535799","Serangoon Lane","","","","","","","1.3463","103.8779",""],"535800":["SG","535800","Serangoon Lane","","","","","","","1.3459","103.8778",""],"535801":["SG","535801","Serangoon Lane","","","","","","","1.3463","103.8779",""],"535802":["SG","535802","Serangoon Lane","","","","","","","1.346","103.8779",""],"535803":["SG","535803","Serangoon Lane","","","","","","","1.3463","103.878",""],"535804":["SG","535804","Serangoon Lane","","","","","","","1.346","103.878",""],"535805":["SG","535805","Serangoon Lane","","","","","","","1.346","103.878",""],"535814":["SG","535814","Rochdale Road","","","","","","","1.3435","103.8834",""],"535815":["SG","535815","Rochdale Road","","","","","","","1.3431","103.8837",""],"535816":["SG","535816","Rochdale Road","","","","","","","1.3435","103.8834",""],"535817":["SG","535817","Rochdale Road","","","","","","","1.3431","103.8837",""],"535818":["SG","535818","Rochdale Road","","","","","","","1.3435","103.8834",""],"535819":["SG","535819","Rochdale Road","","","","","","","1.3431","103.8837",""],"535820":["SG","535820","Rochdale Road","","","","","","","1.3435","103.8834",""],"535821":["SG","535821","Rochdale Road","","","","","","","1.3431","103.8837",""],"535822":["SG","535822","Rochdale Road","","","","","","","1.3435","103.8835",""],"535823":["SG","535823","Rochdale Road","","","","","","","1.3432","103.8837",""],"535824":["SG","535824","Rochdale Road","","","","","","","1.3435","103.8835",""],"535825":["SG","535825","Rochdale Road","","","","","","","1.3432","103.8837",""],"535827":["SG","535827","Rochdale Road","","","","","","","1.3432","103.8838",""],"535828":["SG","535828","Rochdale Road","","","","","","","1.3432","103.8838",""],"535829":["SG","535829","Rochdale Road","","","","","","","1.3436","103.8835",""],"535830":["SG","535830","Rochdale Road","","","","","","","1.3435","103.8842",""],"535831":["SG","535831","Rochdale Road","","","","","","","1.3436","103.8835",""],"535832":["SG","535832","Rochdale Road","","","","","","","1.3435","103.8843",""],"535833":["SG","535833","Rochdale Road","","","","","","","1.3436","103.8844",""],"535834":["SG","535834","Rochdale Road","","","","","","","1.3436","103.8836",""],"535835":["SG","535835","Rochdale Road","","","","","","","1.3436","103.8836",""],"535836":["SG","535836","Rochdale Road","","","","","","","1.3436","103.8845",""],"535837":["SG","535837","Rochdale Road","","","","","","","1.3438","103.8839",""],"535838":["SG","535838","Rochdale Road","","","","","","","1.3437","103.8847",""],"535839":["SG","535839","Rochdale Road","","","","","","","1.3438","103.8841",""],"535840":["SG","535840","Rochdale Road","","","","","","","1.344","103.8842",""],"535841":["SG","535841","Rochdale Road","","","","","","","1.344","103.8843",""],"535842":["SG","535842","Rochdale Road","","","","","","","1.344","103.8844",""],"535843":["SG","535843","Rochdale Road","","","","","","","1.3441","103.8846",""],"535844":["SG","535844","Rochdale Road","","","","","","","1.3437","103.8837",""],"535845":["SG","535845","Rochdale Road","","","","","","","1.3438","103.8838",""],"535846":["SG","535846","Rochdale Road","","","","","","","1.3441","103.8845",""],"535847":["SG","535847","Rochdale Road","","","","","","","1.3436","103.8845",""],"535848":["SG","535848","Rochdale Road","","","","","","","1.3435","103.8843",""],"535852":["SG","535852","Quemoy Road","","","","","","","1.3445","103.8817",""],"535853":["SG","535853","Quemoy Road","","","","","","","1.3444","103.8816",""],"535854":["SG","535854","Quemoy Road","","","","","","","1.3444","103.8816",""],"535855":["SG","535855","Quemoy Road","","","","","","","1.3444","103.8816",""],"535856":["SG","535856","Quemoy Road","","","","","","","1.3444","103.8815",""],"535857":["SG","535857","Quemoy Road","","","","","","","1.3443","103.8815",""],"535858":["SG","535858","Quemoy Road","","","","","","","1.3443","103.8814",""],"535859":["SG","535859","Quemoy Road","","","","","","","1.3442","103.8814",""],"535860":["SG","535860","Quemoy Road","","","","","","","1.3443","103.8812",""],"535861":["SG","535861","Quemoy Road","","","","","","","1.3441","103.8813",""],"535862":["SG","535862","Quemoy Road","","","","","","","1.3442","103.8812",""],"535863":["SG","535863","Quemoy Road","","","","","","","1.3441","103.8811",""],"535864":["SG","535864","Quemoy Road","","","","","","","1.344","103.8811",""],"535865":["SG","535865","Quemoy Road","","","","","","","1.344","103.8811",""],"535866":["SG","535866","Quemoy Road","","","","","","","1.344","103.881",""],"535867":["SG","535867","Quemoy Road","","","","","","","1.3439","103.881",""],"535876":["SG","535876","Pillai Road","","","","","","","1.3473","103.8799",""],"535877":["SG","535877","Pillai Road","","","","","","","1.3473","103.8799",""],"535878":["SG","535878","Pillai Road","","","","","","","1.3477","103.8799",""],"535879":["SG","535879","Pillai Road","","","","","","","1.3477","103.8799",""],"535880":["SG","535880","Pillai Road","","","","","","","1.3473","103.8799",""],"535881":["SG","535881","Pillai Road","","","","","","","1.3473","103.8799",""],"535882":["SG","535882","Pillai Road","","","","","","","1.3476","103.8799",""],"535883":["SG","535883","Pillai Road","","","","","","","1.3476","103.8799",""],"535884":["SG","535884","Pillai Road","","","","","","","1.3472","103.8798",""],"535885":["SG","535885","Pillai Road","","","","","","","1.3472","103.8798",""],"535886":["SG","535886","Pillai Road","","","","","","","1.3476","103.8798",""],"535887":["SG","535887","Pillai Road","","","","","","","1.3476","103.8798",""],"535888":["SG","535888","Pillai Road","","","","","","","1.3472","103.8797",""],"535889":["SG","535889","Pillai Road","","","","","","","1.3472","103.8797",""],"535890":["SG","535890","Pillai Road","","","","","","","1.3475","103.8797",""],"535891":["SG","535891","Pillai Road","","","","","","","1.3475","103.8797",""],"535892":["SG","535892","Pillai Road","","","","","","","1.3471","103.8797",""],"535893":["SG","535893","Pillai Road","","","","","","","1.3471","103.8797",""],"535894":["SG","535894","Pillai Road","","","","","","","1.3475","103.8797",""],"535895":["SG","535895","Pillai Road","","","","","","","1.3475","103.8797",""],"535896":["SG","535896","Pillai Road","","","","","","","1.3471","103.8796",""],"535897":["SG","535897","Pillai Road","","","","","","","1.3471","103.8796",""],"535898":["SG","535898","Pillai Road","","","","","","","1.3474","103.8796",""],"535899":["SG","535899","Pillai Road","","","","","","","1.3474","103.8796",""],"535900":["SG","535900","Pillai Road","","","","","","","1.347","103.8795",""],"535901":["SG","535901","Pillai Road","","","","","","","1.347","103.8795",""],"535902":["SG","535902","Pillai Road","","","","","","","1.3474","103.8795",""],"535903":["SG","535903","Pillai Road","","","","","","","1.3473","103.8795",""],"535904":["SG","535904","Pillai Road","","","","","","","1.347","103.8795",""],"535905":["SG","535905","Pillai Road","","","","","","","1.347","103.8795",""],"535906":["SG","535906","Pillai Road","","","","","","","1.3473","103.8795",""],"535907":["SG","535907","Pillai Road","","","","","","","1.3473","103.8795",""],"535908":["SG","535908","Pillai Road","","","","","","","1.3469","103.8794",""],"535909":["SG","535909","Pillai Road","","","","","","","1.3469","103.8794",""],"535910":["SG","535910","Pillai Road","","","","","","","1.3473","103.8794",""],"535911":["SG","535911","Pillai Road","","","","","","","1.3473","103.8794",""],"535912":["SG","535912","Pillai Road","","","","","","","1.3469","103.8793",""],"535913":["SG","535913","Pillai Road","","","","","","","1.3469","103.8793",""],"535914":["SG","535914","Pillai Road","","","","","","","1.3472","103.8793",""],"535915":["SG","535915","Pillai Road","","","","","","","1.3472","103.8793",""],"535916":["SG","535916","Pillai Road","","","","","","","1.3468","103.8793",""],"535926":["SG","535926","Paya Lebar Walk","","","","","","","1.3487","103.8806",""],"535927":["SG","535927","Paya Lebar Walk","","","","","","","1.3487","103.8807",""],"535928":["SG","535928","Paya Lebar Walk","","","","","","","1.3487","103.8807",""],"535929":["SG","535929","Paya Lebar Walk","","","","","","","1.3487","103.8808",""],"535930":["SG","535930","Paya Lebar Walk","","","","","","","1.3488","103.8808",""],"535931":["SG","535931","Paya Lebar Walk","","","","","","","1.3488","103.8809",""],"535932":["SG","535932","Paya Lebar Walk","","","","","","","1.3488","103.8809",""],"535933":["SG","535933","Paya Lebar Walk","","","","","","","1.3488","103.881",""],"535934":["SG","535934","Paya Lebar Walk","","","","","","","1.3485","103.8811",""],"535935":["SG","535935","Paya Lebar Walk","","","","","","","1.3488","103.8811",""],"535936":["SG","535936","Paya Lebar Walk","","","","","","","1.3485","103.8811",""],"535937":["SG","535937","Paya Lebar Walk","","","","","","","1.3488","103.8812",""],"535938":["SG","535938","Paya Lebar Walk","","","","","","","1.3485","103.8812",""],"535939":["SG","535939","Paya Lebar Walk","","","","","","","1.3489","103.8812",""],"535940":["SG","535940","Paya Lebar Walk","","","","","","","1.3485","103.8812",""],"535941":["SG","535941","Paya Lebar Walk","","","","","","","1.3489","103.8813",""],"535942":["SG","535942","Paya Lebar Walk","","","","","","","1.3485","103.8813",""],"535943":["SG","535943","Paya Lebar Walk","","","","","","","1.3489","103.8813",""],"535944":["SG","535944","Paya Lebar Walk","","","","","","","1.3485","103.8814",""],"535945":["SG","535945","Paya Lebar Walk","","","","","","","1.3489","103.8814",""],"535946":["SG","535946","Paya Lebar Walk","","","","","","","1.3486","103.8814",""],"535947":["SG","535947","Paya Lebar Walk","","","","","","","1.3489","103.8814",""],"535948":["SG","535948","Paya Lebar Walk","","","","","","","1.3487","103.8816",""],"535949":["SG","535949","Paya Lebar Walk","","","","","","","1.3489","103.8815",""],"535950":["SG","535950","Paya Lebar Walk","","","","","","","1.3486","103.8816",""],"535951":["SG","535951","Paya Lebar Walk","","","","","","","1.3489","103.8815",""],"535952":["SG","535952","Paya Lebar Walk","","","","","","","1.3486","103.8816",""],"535953":["SG","535953","Paya Lebar Walk","","","","","","","1.3489","103.8816",""],"535954":["SG","535954","Paya Lebar Walk","","","","","","","1.3485","103.8816",""],"535955":["SG","535955","Paya Lebar Walk","","","","","","","1.349","103.8818",""],"535956":["SG","535956","Paya Lebar Walk","","","","","","","1.3484","103.8816",""],"535957":["SG","535957","Paya Lebar Walk","","","","","","","1.349","103.8818",""],"535958":["SG","535958","Paya Lebar Walk","","","","","","","1.3489","103.8819",""],"535959":["SG","535959","Paya Lebar Walk","","","","","","","1.3489","103.8819",""],"535960":["SG","535960","Paya Lebar Walk","","","","","","","1.3488","103.8819",""],"535961":["SG","535961","Paya Lebar Walk","","","","","","","1.3488","103.8819",""],"535962":["SG","535962","Paya Lebar Walk","","","","","","","1.3487","103.8819",""],"535963":["SG","535963","Paya Lebar Walk","","","","","","","1.3487","103.8819",""],"535964":["SG","535964","Paya Lebar Walk","","","","","","","1.3486","103.8819",""],"535965":["SG","535965","Paya Lebar Walk","","","","","","","1.3485","103.8819",""],"535966":["SG","535966","Paya Lebar Walk","","","","","","","1.3485","103.8819",""],"535967":["SG","535967","Paya Lebar Walk","","","","","","","1.3487","103.8806",""],"535975":["SG","535975","Paya Lebar Street","","","","","","","1.339","103.885",""],"535976":["SG","535976","Paya Lebar Street","","","","","","","1.339","103.885",""],"535977":["SG","535977","Paya Lebar Street","","","","","","","1.3391","103.885",""],"535978":["SG","535978","Paya Lebar Street","","","","","","","1.3391","103.8849",""],"535979":["SG","535979","Paya Lebar Street","","","","","","","1.3392","103.8849",""],"535980":["SG","535980","Paya Lebar Street","","","","","","","1.3393","103.8847",""],"535981":["SG","535981","Paya Lebar Street","","","","","","","1.3393","103.8848",""],"535982":["SG","535982","Paya Lebar Street","","","","","","","1.3394","103.8848",""],"535983":["SG","535983","Paya Lebar Street","","","","","","","1.3394","103.8849",""],"535984":["SG","535984","Paya Lebar Street","","","","","","","1.3394","103.8849",""],"535985":["SG","535985","Paya Lebar Street","","","","","","","1.3395","103.8849",""],"535986":["SG","535986","Buangkok Crescent","","","","","","","1.383","103.8805",""],"535991":["SG","535991","Buangkok Link","","","","","","","1.3838","103.8825",""],"535994":["SG","535994","Paya Lebar Place","","","","","","","1.3495","103.8813",""],"535995":["SG","535995","Paya Lebar Place","","","","","","","1.3495","103.8813",""],"535996":["SG","535996","Paya Lebar Place","","","","","","","1.3495","103.8812",""],"535997":["SG","535997","Paya Lebar Place","","","","","","","1.3494","103.8812",""],"535998":["SG","535998","Paya Lebar Place","","","","","","","1.3491","103.8812",""],"535999":["SG","535999","Paya Lebar Place","","","","","","","1.3491","103.8813",""]}